postgres_database_utils/__init__.py
postgres_database_utils/main.py
postgres_database_utils-1.1.0.dist-info/LICENSE
postgres_database_utils-1.1.0.dist-info/METADATA
postgres_database_utils-1.1.0.dist-info/WHEEL
postgres_database_utils-1.1.0.dist-info/top_level.txt
postgres_database_utils-1.1.0.dist-info/RECORD
