Metadata-Version: 2.1
Name: postgres-database-utils
Version: 1.1.0
Summary: A package for postgres database utilities
Home-page: https://github.com/apinanyogaratnam/database-utils
Author: apinanyogaratnam
Author-email: apinanapinan@icloud.com
Classifier: Programming Language :: Python :: 3
Classifier: License :: OSI Approved :: MIT License
Classifier: Operating System :: OS Independent
Requires-Python: >=3.10.4
License-File: LICENSE
Requires-Dist: psycopg2-binary
Requires-Dist: pandas
